mu_pygrader-1.0.8.dist-info/licenses/LICENSE.txt
mupygrader/__init__.py
mupygrader/assignment.py
mupygrader/json_interface.py
mupygrader/pgrader_gui.py
mupygrader/test_file.py
mupygrader/utils.py
mu_pygrader-1.0.8.dist-info/METADATA
mu_pygrader-1.0.8.dist-info/WHEEL
mu_pygrader-1.0.8.dist-info/top_level.txt
mu_pygrader-1.0.8.dist-info/RECORD
