Metadata-Version: 2.4
Name: mu-pygrader
Version: 1.0.8
Summary: Grader tools for ENGR 212 at Messiah
Author-email: Ben Weaver <bweaver2@messiah.edu>
License-File: LICENSE.txt
Requires-Dist: numpy
Requires-Dist: pandas
Requires-Dist: pyinstaller
Dynamic: license-file
